ug_tagung/Icons.yaml
ug_tagung/Override.yaml
ug_tagung/Tagung.py
ug_tagung/Tagung.sh
ug_tagung/Tagung.yaml
ug_tagung/TagungInstall.ps1
ug_tagung/TagungInstall.sh
ug_tagung/TagungStart.ps1
ug_tagung/TagungStart.sh
ug_tagung/TagungUpgrade.ps1
ug_tagung/TagungUpgrade.sh
ug_tagung/Tagung_Def.py
ug_tagung/Tagung_Modelle.py
ug_tagung/__init__.py
ug_tagung-1.3.18.dist-info/METADATA
ug_tagung-1.3.18.dist-info/WHEEL
ug_tagung-1.3.18.dist-info/licenses/LICENSE
ug_tagung-1.3.18.dist-info/RECORD
